{
    "type": "function",
    "function": {
        "name": "compare",
        "description": "Compare two number, which one is bigger",
        "parameters": {
            "type": "object",
            "properties": {
                "a": {
                    "type": "number",
                    "description": "A number"
                },
                "b": {
                    "type": "number",
                    "description": "A number"
                }
            },
            "required": ["a", "b"]
        }
    }
}